simpleN/__init__.py
simpleN/analyze.py
simpleN/net.py
simpleN/visual.py
simpleN/link/__init__.py
simpleN/link/advance.py
simpleN/link/simple.py
simpleN/link/target.py
simpleN/link/withattrs.py
Simple_Network-3.1.1.dist-info/LICENSE
Simple_Network-3.1.1.dist-info/METADATA
Simple_Network-3.1.1.dist-info/WHEEL
Simple_Network-3.1.1.dist-info/top_level.txt
Simple_Network-3.1.1.dist-info/RECORD
