Metadata-Version: 2.1
Name: Simple-Network
Version: 3.1.1
Summary: A basic tool designed for the construction and visualization of complex, multilayer networks.
Home-page: https://github.com/cloner174/Simple-Network
Author: Hamed Hajipour
Author-email: Hamed Hajipour <cloner174.org@gmail.com>
Project-URL: Homepage, https://github.com/cloner174/Simple-Network
Project-URL: Documentation, https://github.com/cloner174/Simple-Network#readme
Project-URL: Repository, https://github.com/cloner174/Simple-Network
Project-URL: Issues, https://github.com/cloner174/Simple-Network/issues
Classifier: Programming Language :: Python :: 3
Classifier: Programming Language :: Python :: 3.6
Classifier: Programming Language :: Python :: 3.7
Classifier: Programming Language :: Python :: 3.8
Classifier: Programming Language :: Python :: 3.9
Classifier: Programming Language :: Python :: 3.10
Classifier: Programming Language :: Python :: 3.11
Classifier: Programming Language :: Python :: 3.12
Classifier: License :: OSI Approved :: MIT License
Classifier: Operating System :: OS Independent
Requires-Python: >=3.6
License-File: LICENSE
Requires-Dist: plotly
Requires-Dist: numpy
